anywebscraper/__init__.py
anywebscraper/anywebscraper.py
anywebscraper/test.py
anywebscraper/images/__init__.py
anywebscraper-0.1.3.dist-info/METADATA
anywebscraper-0.1.3.dist-info/WHEEL
anywebscraper-0.1.3.dist-info/top_level.txt
anywebscraper-0.1.3.dist-info/RECORD
