Metadata-Version: 2.1
Name: anywebscraper
Version: 0.1.3
Summary: anywebscraper is your ultimate web data extraction companion. We understand the challenges of web scraping, including dealing with anti-bot measures and the need for reliable proxies. We make web scraping easy and effective, even in the most challenging environments. Whether you're a data scientist, business analyst or developer looking to harness the power of web data, anywebscraper has you covered.
Home-page: https://github.com/pierjosvins/anywebscraper
Author: Pierjos COLERE
Author-email: colerepierjos30@gmail.com
Classifier: License :: OSI Approved :: MIT License
Classifier: Programming Language :: Python
Classifier: Programming Language :: Python :: 3
Classifier: Programming Language :: Python :: 3.6
Classifier: Programming Language :: Python :: 3.7
Classifier: Programming Language :: Python :: 3.8
Classifier: Programming Language :: Python :: 3.9
Classifier: Programming Language :: Python :: Implementation :: PyPy
Classifier: Operating System :: Unix
Classifier: Operating System :: MacOS :: MacOS X
Classifier: Operating System :: Microsoft :: Windows
Requires-Python: >=3.6.0
Requires-Dist: beautifulsoup4 ==4.12.2
Requires-Dist: bs4 ==0.0.1
Requires-Dist: soupsieve ==2.4.1
Requires-Dist: gdown ==4.7.1
